odoo/addons/sales_team_security_sale/README.rst
odoo/addons/sales_team_security_sale/__init__.py
odoo/addons/sales_team_security_sale/__manifest__.py
odoo/addons/sales_team_security_sale/i18n/it.po
odoo/addons/sales_team_security_sale/i18n/sales_team_security_sale.pot
odoo/addons/sales_team_security_sale/readme/CONFIGURE.md
odoo/addons/sales_team_security_sale/readme/CONTRIBUTORS.md
odoo/addons/sales_team_security_sale/readme/DESCRIPTION.md
odoo/addons/sales_team_security_sale/security/security.xml
odoo/addons/sales_team_security_sale/static/description/icon.png
odoo/addons/sales_team_security_sale/static/description/index.html
odoo/addons/sales_team_security_sale/tests/__init__.py
odoo/addons/sales_team_security_sale/tests/test_sales_team_security_sale.py
odoo_addon_sales_team_security_sale-17.0.1.0.0.3.dist-info/METADATA
odoo_addon_sales_team_security_sale-17.0.1.0.0.3.dist-info/WHEEL
odoo_addon_sales_team_security_sale-17.0.1.0.0.3.dist-info/top_level.txt
odoo_addon_sales_team_security_sale-17.0.1.0.0.3.dist-info/RECORD
