Metadata-Version: 2.1
Name: odoo-addon-sales_team_security_sale
Version: 17.0.1.0.0.3
Requires-Python: >=3.10
Requires-Dist: odoo-addon-sales_team_security>=17.0dev,<17.1dev
Requires-Dist: odoo>=17.0a,<17.1dev
Summary: Integrates sales_team_security with sale
Home-page: https://github.com/OCA/sale-workflow
License: AGPL-3
Author: =?utf-8?q?Tecnativa=2C_Iv=C3=A1n_Todorovich=2C_Odoo_Community_Association_=28OCA=29?=
Author-email: support@odoo-community.org
Classifier: Programming Language :: Python
Classifier: Framework :: Odoo
Classifier: Framework :: Odoo :: 17.0
Classifier: License :: OSI Approved :: GNU Affero General Public License v3
Classifier: Development Status :: 5 - Production/Stable
